golden_marshmallows/__init__.py
golden_marshmallows/schema.py
golden_marshmallows-1.0.0.dist-info/LICENSE
golden_marshmallows-1.0.0.dist-info/METADATA
golden_marshmallows-1.0.0.dist-info/WHEEL
golden_marshmallows-1.0.0.dist-info/top_level.txt
golden_marshmallows-1.0.0.dist-info/RECORD
