Metadata-Version: 2.1
Name: golden-marshmallows
Version: 1.0.0
Summary: Marshmallow Schema subclass that auto-defines fields based on SQLAlchemy classes
Home-page: https://github.com/gchorn/golden-marshmallows
Author: Guillaume Chorn
Author-email: guillaume.chorn@gmail.com
License: UNKNOWN
Download-URL: https://github.com/gchorn/golden-marshmallows/archive/v1.0.0.tar.gz
Platform: UNKNOWN
Requires-Dist: marshmallow
Requires-Dist: SQLAlchemy
